[
    {
        "id": "8da442db",
        "cliente_id": 1,
        "metragem": 233.0,
        "portao": "sim",
        "valor_estimado": 2449.0,
        "material": "pvc",
        "t_painel": "6x6",
        "cor_material": "branco",
        "tamanho_portao": null,
        "qnt_portao": 2,
        "portoes": {
            "portao_1": "single",
            "portao_2": "double"
        }
    },
    {
        "id": "537c8d17",
        "cliente_id": 1,
        "metragem": 123.0,
        "portao": "sim",
        "valor_estimado": 1233.0,
        "material": "pvc",
        "t_painel": "6x6",
        "cor_material": "branco",
        "tamanho_portao": null,
        "qnt_portao": 1,
        "portoes": {
            "portao_1": "double"
        }
    },
    {
        "id": "7a95c1d2",
        "cliente_id": 2,
        "metragem": 123.0,
        "portao": "sim",
        "valor_estimado": 3202.0,
        "material": "pvc",
        "t_painel": "6x6",
        "cor_material": "branco",
        "tamanho_portao": null,
        "qnt_portao": 1,
        "portoes": {
            "portao_1": "single"
        }
    },
    {
        "id": "5d5f872d",
        "cliente_id": 1,
        "metragem": 234.0,
        "portao": "sim",
        "valor_estimado": 6116.0,
        "material": "pvc",
        "t_painel": "6x6",
        "cor_material": "branco",
        "tamanho_portao": null,
        "qnt_portao": 2,
        "portoes": {
            "portao_1": "single",
            "portao_2": "double"
        }
    },
    {
        "id": "1648fbac",
        "cliente_id": 1,
        "metragem": 234.0,
        "portao": "sim",
        "valor_estimado": 6568.0,
        "material": "pvc",
        "t_painel": "6x8",
        "cor_material": "branco",
        "tamanho_portao": null,
        "qnt_portao": 1,
        "portoes": {
            "portao_1": "double"
        }
    }
]